schneiderl_md2cf/__init__.py
schneiderl_md2cf/__main__.py
schneiderl_md2cf/api.py
schneiderl_md2cf/confluence_renderer.py
schneiderl_md2cf/console_output.py
schneiderl_md2cf/document.py
schneiderl_md2cf/ignored_files.py
schneiderl_md2cf/tui.py
schneiderl_md2cf/upsert.py
schneiderl_md2cf-0.99.99.dist-info/LICENSE
schneiderl_md2cf-0.99.99.dist-info/METADATA
schneiderl_md2cf-0.99.99.dist-info/WHEEL
schneiderl_md2cf-0.99.99.dist-info/entry_points.txt
schneiderl_md2cf-0.99.99.dist-info/top_level.txt
schneiderl_md2cf-0.99.99.dist-info/RECORD
