Metadata-Version: 2.1
Name: schneiderl-md2cf
Version: 0.99.99
Summary: Convert Markdown documents to Confluence
Home-page: https://github.com/schneiderl/md2cf
Author: schneiderl
Author-email: schneiderl@schneiderl.com
License: MIT
Keywords: markdown confluence
Platform: UNKNOWN
Classifier: Programming Language :: Python :: 3
Classifier: License :: OSI Approved :: MIT License
Classifier: Operating System :: OS Independent
Requires-Python: >=3.7
Requires-Dist: rich-argparse ==1.0.0
Requires-Dist: rich ==13.0.1
Requires-Dist: mistune ==3.0.1
Requires-Dist: chardet ==5.1.0
Requires-Dist: requests ==2.31.0
Requires-Dist: PyYAML ==6.0.1
Requires-Dist: gitignorefile ==1.1.2
